tests/__init__.py
tests/test_example.py
tests/test_fair_distributor.py
vania/__init__.py
vania/fair_distributor.py
vania/vania.py
vania-0.2.0.dist-info/DESCRIPTION.rst
vania-0.2.0.dist-info/METADATA
vania-0.2.0.dist-info/RECORD
vania-0.2.0.dist-info/WHEEL
vania-0.2.0.dist-info/metadata.json
vania-0.2.0.dist-info/top_level.txt
