Metadata-Version: 2.0
Name: vania
Version: 0.2.0
Summary: A module to fairly distribute objects among targets considering weights.
Home-page: UNKNOWN
Author: Hackathonners
Author-email: contact@hackathonners.org
License: MIT
Platform: UNKNOWN
Classifier: Programming Language :: Python
Classifier: Programming Language :: Python :: 3
Requires-Dist: pdoc
Requires-Dist: pulp
